unieai_mcp_accton_rfp/StressTest.py
unieai_mcp_accton_rfp/__init__.py
unieai_mcp_accton_rfp/server.py
unieai_mcp_accton_rfp/server_old.py
unieai_mcp_accton_rfp/server_release_v1.py
unieai_mcp_accton_rfp/server_v0.py
unieai_mcp_accton_rfp/server_v1.py
unieai_mcp_accton_rfp/server_v12.py
unieai_mcp_accton_rfp/server_v2.py
unieai_mcp_accton_rfp/server_v3.py
unieai_mcp_accton_rfp/server_v4.py
unieai_mcp_accton_rfp/server_v6.py
unieai_mcp_accton_rfp/server_v7.py
unieai_mcp_accton_rfp/server_v9.py
unieai_mcp_accton_rfp/test.py
unieai_mcp_accton_rfp-0.0.26.dist-info/licenses/LICENSE
unieai_mcp_accton_rfp-0.0.26.dist-info/METADATA
unieai_mcp_accton_rfp-0.0.26.dist-info/WHEEL
unieai_mcp_accton_rfp-0.0.26.dist-info/entry_points.txt
unieai_mcp_accton_rfp-0.0.26.dist-info/top_level.txt
unieai_mcp_accton_rfp-0.0.26.dist-info/RECORD
