Metadata-Version: 2.4
Name: unieai_mcp_accton_rfp
Version: 0.0.26
Summary: Internal MCP server for Accton RFP automation (UnieAI)
Home-page: https://www.unieai.com/
Author: UnieAI
Author-email: contact@unieai.com
License: Proprietary
Classifier: Programming Language :: Python :: 3
Classifier: License :: Other/Proprietary License
Classifier: Operating System :: OS Independent
Requires-Python: >=3.8
License-File: LICENSE
Requires-Dist: fastmcp>=0.3.0
Requires-Dist: fastapi>=0.104.0
Requires-Dist: pydantic>=2.0.0
Requires-Dist: python-dotenv>=1.0.1
Requires-Dist: requests>=2.31.0
Requires-Dist: openpyxl>=3.1.5
Requires-Dist: httpx>=0.24.0
Requires-Dist: openai>=1.35.10
Requires-Dist: langchain>=0.3.7
Requires-Dist: langchain-core>=0.3.9
Requires-Dist: langchain-openai>=0.2.3
Requires-Dist: aiohttp>=3.9.5
Requires-Dist: tiktoken>=0.7.0
Requires-Dist: rich>=13.7.1
Requires-Dist: tenacity>=8.3.0
Dynamic: license-file
